[
    {
        "thread_id": "1000",
        "sn": "0",
        "subject": "English Language",
        "topic": "parts of speech",
        "post_title": "What is the meaning of a noun",
        "post_text": "I am having some issues understanding the concept of nouns, please can someone help me out with it meaning. Thanks",
        "orginal_poster": "Chinedu Ekene Okpala",
        "orginal_posterid": "GSIS09882",
        "post_date_time": "March 2, 2018, at 4: 51PM",
        "user_signature": "Life is short. There are more things we still do not know.",
        "votes": "3",
        "views": "11",
        "answers": "2",
        "szclass": "JSS 2",
        "schoolid": "GSISCHOOL"
    },
    {
        "thread_id": "1000",
        "sn": "1",
        "subject": "English Language",
        "topic": "parts of speech",
        "post_title": "Re: What is the meaning of a noun",
        "post_text": "A noun is a part of speech, and parts of speech simply refer to types of words. You may be familiar with a lot of basic parts of speech, like nouns, verbs, and adjectives. Nouns identify people, places, things, and ideas. Nouns can be categorized as either common or proper. Common nouns name general people, places, things, and ideas, while proper nouns name specificpeople, places, things, and ideas. for more info check out: <a href='https:\/\/study.com\/academy\/lesson\/what-are-nouns-definition-types-examples.html'> What Are Nouns? - Definition, Types & Examples<\/a>",
        "orginal_poster": "James Kwesi",
        "orginal_posterid": "GSIS08463",
        "post_date_time": "March 2, 2018, at 5:05PM",
        "user_signature": "Keep Learning...",
        "votes": "4",
        "views": "11",
        "answers": "2",
        "szclass": "JSS 2",
        "schoolid": "GSISCHOOL"
    },
    {
        "thread_id": "1001",
        "sn": "0",
        "subject": "English Language",
        "topic": "parts of speech",
        "post_title": "What is the meaning of a Verb",
        "post_text": "A noun is a part of speech, and parts of speech simply refer to types of words. You may be familiar with a lot of basic parts of speech, like nouns, verbs, and adjectives. Nouns identify people, places, things, and ideas. Nouns can be categorized as either common or proper. Common nouns name general people, places, things, and ideas, while proper nouns name specificpeople, places, things, and ideas. for more info check out: <a href='https:\/\/study.com\/academy\/lesson\/what-are-nouns-definition-types-examples.html'> What Are Nouns? - Definition, Types & Examples<\/a>",
        "orginal_poster": "James Kwesi",
        "orginal_posterid": "GSIS08463",
        "post_date_time": "March 18, 2018, at 5:05PM",
        "user_signature": "Keep Learning...",
        "votes": "1",
        "views": "7",
        "answers": "2",
        "szclass": "JSS 2",
        "schoolid": "GSISCHOOL"
    },
    {
        "thread_id": "1000",
        "sn": "2",
        "subject": "English Language",
        "topic": "parts of speech",
        "post_title": "Re: What is the meaning of a noun",
        "post_text": "jdkabdiuaeabifbadakjcbz\\kd.cvjbd",
        "orginal_poster": "Chinedu Ekene Okpala",
        "orginal_posterid": "GSIS09882",
        "post_date_time": "March 20, 2018, at 04:32 AM",
        "user_signature": "Life is short. There are more things we still do not know.",
        "votes": "2",
        "views": "11",
        "answers": "2",
        "szclass": "JSS 2",
        "schoolid": "GSISCHOOL"
    },
    {
        "thread_id": "1001",
        "sn": "1",
        "subject": "English Language",
        "topic": "parts of speech",
        "post_title": "Re: What is the meaning of a Verb",
        "post_text": "testing the mic",
        "orginal_poster": "Chinedu Ekene Okpala",
        "orginal_posterid": "GSIS09882",
        "post_date_time": "March 20, 2018, at 04:37 AM",
        "user_signature": "Life is short. There are more things we still do not know.",
        "votes": "2",
        "views": "6",
        "answers": "2",
        "szclass": "JSS 2",
        "schoolid": "GSISCHOOL"
    },
    {
        "thread_id": "1001",
        "sn": "2",
        "subject": "English Language",
        "topic": "parts of speech",
        "post_title": "Re: What is the meaning of a Verb",
        "post_text": "gggggggggggg",
        "orginal_poster": "Chinedu Ekene Okpala",
        "orginal_posterid": "GSIS09882",
        "post_date_time": "March 20, 2018, at 04:50 AM",
        "user_signature": "Life is short. There are more things we still do not know.",
        "votes": "0",
        "views": "7",
        "answers": "2",
        "szclass": "JSS 2",
        "schoolid": "GSISCHOOL"
    },
    {
        "thread_id": "1002",
        "sn": "0",
        "subject": "Biology",
        "topic": "Cell",
        "post_title": "What is amoba",
        "post_text": "<p>epp me<\/p>",
        "orginal_poster": "Chinedu Ekene Okpala",
        "orginal_posterid": "GSIS09882",
        "post_date_time": "March 23, 2018, at 09:12 PM",
        "user_signature": "Life is short. There are more things we still do not know.",
        "votes": "1",
        "views": "1",
        "answers": 1,
        "szclass": "JSS 2",
        "schoolid": "GSISCHOOL"
    },
    {
        "thread_id": "1002",
        "sn": 1,
        "subject": "Biology",
        "topic": "Cell",
        "post_title": "Re: What is amoba",
        "post_text": "lllllllllllllllll",
        "orginal_poster": "Chinedu Ekene Okpala",
        "orginal_posterid": "GSIS09882",
        "post_date_time": "March 23, 2018, at 10:10 PM",
        "user_signature": "Life is short. There are more things we still do not know.",
        "votes": 2,
        "views": "1",
        "answers": 1,
        "szclass": "JSS 2",
        "schoolid": "GSISCHOOL"
    },
    {
        "thread_id": "1003",
        "sn": "0",
        "subject": "Mathematics",
        "topic": "Factorial",
        "post_title": "Factorizing Complex Number",
        "post_text": "<p>Please i have this math question<\/p><p>Factor 3x<sup>3<\/sup> - x<sup>2<\/sup>y +6x<sup>2<\/sup>y - 2xy<sup>2<\/sup> + 3xy<sup>2<\/sup> - y<sup>3<\/sup> =<\/p>",
        "orginal_poster": "Chinedu Ekene Okpala",
        "orginal_posterid": "GSIS09882",
        "post_date_time": "March 23, 2018, at 10:21 PM",
        "user_signature": "Life is short. There are more things we still do not know.",
        "votes": 7,
        "views": "3",
        "answers": "0",
        "szclass": "JSS 2",
        "schoolid": "GSISCHOOL"
    }
]